<?xml version="1.0" encoding="utf-8" ?>
<SQLSatement>
  <sql>
    <![CDATA[
UPDATE InternalMethod SET ClassifyID={0} WHERE MethodID IN ({1})
    ]]>
  </sql>
  <!--operatetype: 0 Query(multi-records); 1 DDL(insert update etc); 2 Single(single record)-->
  <operatetype>1</operatetype>
  <!--paramtype: 0 Normal; 1 Parames; 2 Format-->
  <paramtype>2</paramtype> 
  <sqlparames></sqlparames>
  <formatdetails>
    <formatinfo>
      <key>1</key>
      <desc>ClassifyID</desc>
      <mockdata>1</mockdata>
      <realdata></realdata>
    </formatinfo>
	<formatinfo>
      <key>2</key>
      <desc>MethodID</desc>
      <mockdata>1,2,3,4</mockdata>
      <realdata></realdata>
    </formatinfo>
  </formatdetails>
</SQLSatement>
